searxng_mcp/__init__.py
searxng_mcp/__main__.py
searxng_mcp/mcp_config.json
searxng_mcp/middlewares.py
searxng_mcp/searxng_agent.py
searxng_mcp/searxng_mcp.py
searxng_mcp/utils.py
searxng_mcp/skills/searxng-search/SKILL.md
searxng_mcp-0.0.21.dist-info/licenses/LICENSE
searxng_mcp-0.0.21.dist-info/METADATA
searxng_mcp-0.0.21.dist-info/WHEEL
searxng_mcp-0.0.21.dist-info/entry_points.txt
searxng_mcp-0.0.21.dist-info/top_level.txt
searxng_mcp-0.0.21.dist-info/RECORD
